log_added_func/__init__.py
log_added_func/log.py
log_added_func/log_decorator.py
log_added_func-0.2.2.dist-info/licenses/LICENSE
log_added_func-0.2.2.dist-info/METADATA
log_added_func-0.2.2.dist-info/WHEEL
log_added_func-0.2.2.dist-info/top_level.txt
log_added_func-0.2.2.dist-info/RECORD
