Metadata-Version: 2.4
Name: log_added_func
Version: 0.2.2
Summary: log can be inserted at the desired location.
Home-page: https://github.com/YCkao5888/log_added_func.git
Author: YCKAO
Author-email: kao0983326221@gmail.com
Classifier: Programming Language :: Python :: 3
Classifier: License :: OSI Approved :: MIT License
Requires-Python: >=3
License-File: LICENSE
Requires-Dist: concurrent-log-handler
Requires-Dist: psutil
Dynamic: author
Dynamic: author-email
Dynamic: classifier
Dynamic: description
Dynamic: description-content-type
Dynamic: home-page
Dynamic: license-file
Dynamic: requires-dist
Dynamic: requires-python
Dynamic: summary
